bridge/__init__.py
bridge/exporter.py
python_latex_bridge-0.0.1.dist-info/LICENSE
python_latex_bridge-0.0.1.dist-info/METADATA
python_latex_bridge-0.0.1.dist-info/WHEEL
python_latex_bridge-0.0.1.dist-info/top_level.txt
python_latex_bridge-0.0.1.dist-info/RECORD
