Metadata-Version: 2.1
Name: python-latex-bridge
Version: 0.0.1
Summary: Include python variable values in a LaTeX document
Home-page: https://github.com/timmedia/python-latex-bridge
Author: Tim Mutkala
Author-email: contact@tim-media.com
License: MIT
Platform: UNKNOWN
Classifier: Programming Language :: Python :: 3
Classifier: License :: OSI Approved :: MIT License
Classifier: Operating System :: OS Independent
